genpw/__init__.py
genpw/genpw.py
genpw/trigrams/A.csv
genpw/trigrams/B.csv
genpw/trigrams/C.csv
genpw/trigrams/D.csv
genpw/trigrams/E.csv
genpw/trigrams/F.csv
genpw/trigrams/G.csv
genpw/trigrams/H.csv
genpw/trigrams/I.csv
genpw/trigrams/J.csv
genpw/trigrams/K.csv
genpw/trigrams/L.csv
genpw/trigrams/M.csv
genpw/trigrams/N.csv
genpw/trigrams/O.csv
genpw/trigrams/P.csv
genpw/trigrams/Q.csv
genpw/trigrams/R.csv
genpw/trigrams/S.csv
genpw/trigrams/T.csv
genpw/trigrams/U.csv
genpw/trigrams/V.csv
genpw/trigrams/W.csv
genpw/trigrams/X.csv
genpw/trigrams/Y.csv
genpw/trigrams/Z.csv
genpw-1.0.0.post1.dist-info/LICENSE
genpw-1.0.0.post1.dist-info/METADATA
genpw-1.0.0.post1.dist-info/WHEEL
genpw-1.0.0.post1.dist-info/top_level.txt
genpw-1.0.0.post1.dist-info/RECORD
