Metadata-Version: 2.1
Name: genpw
Version: 1.0.0.post1
Summary: Generate pronounceable passwords in Python.
Home-page: https://github.com/arrai-innovations/genpw/
Author: Arrai Innovations
Author-email: support@arrai.com
License: LICENSE
Platform: UNKNOWN
Classifier: Development Status :: 5 - Production/Stable
Classifier: Programming Language :: Python :: 3
Classifier: Programming Language :: Python :: 3.6
Classifier: Programming Language :: Python :: 3.7
Classifier: Programming Language :: Python :: 3.8
Classifier: License :: OSI Approved :: BSD License
Classifier: Intended Audience :: Developers
